odooupgrader/__init__.py
odooupgrader/__main__.py
odooupgrader/cli.py
odooupgrader/core.py
odooupgrader-0.2.0.dist-info/licenses/LICENSE
odooupgrader-0.2.0.dist-info/METADATA
odooupgrader-0.2.0.dist-info/WHEEL
odooupgrader-0.2.0.dist-info/entry_points.txt
odooupgrader-0.2.0.dist-info/top_level.txt
odooupgrader-0.2.0.dist-info/RECORD
