Metadata-Version: 2.4
Name: odooupgrader
Version: 0.2.0
Summary: Docker-based Odoo database migration tool using OpenUpgrade framework
Author-email: Fasil <fasilwdr@hotmail.com>
License: MIT
Project-URL: Homepage, https://github.com/fasilwdr/OdooUpgrader
Project-URL: Repository, https://github.com/fasilwdr/OdooUpgrader
Project-URL: Documentation, https://github.com/fasilwdr/OdooUpgrader#readme
Project-URL: Issues, https://github.com/fasilwdr/OdooUpgrader/issues
Keywords: odoo,upgrade,openupgrade,database,migration
Classifier: Development Status :: 4 - Beta
Classifier: Intended Audience :: Developers
Classifier: License :: OSI Approved :: MIT License
Classifier: Programming Language :: Python :: 3
Classifier: Programming Language :: Python :: 3.9
Classifier: Programming Language :: Python :: 3.10
Classifier: Programming Language :: Python :: 3.11
Classifier: Programming Language :: Python :: 3.12
Classifier: Programming Language :: Python :: 3.13
Requires-Python: >=3.9
License-File: LICENSE
Requires-Dist: click>=8.1.0
Requires-Dist: rich>=13.7.0
Requires-Dist: requests>=2.31.0
Requires-Dist: packaging>=23.0
Provides-Extra: dev
Requires-Dist: pytest>=7.4.0; extra == "dev"
Requires-Dist: black>=23.0.0; extra == "dev"
Requires-Dist: mypy>=1.7.0; extra == "dev"
Dynamic: license-file
